{"9318314":{"pref":"\u5bcc\u5c71\u770c","addr":"\u5bcc\u5c71\u5e02\u7c9f\u5cf6\u753a"},"9318321":{"pref":"\u5bcc\u5c71\u770c","addr":"\u5bcc\u5c71\u5e02\u72ac\u5cf6"},"9318328":{"pref":"\u5bcc\u5c71\u770c","addr":"\u5bcc\u5c71\u5e02\u72ac\u5cf6\u65b0\u753a"},"9318374":{"pref":"\u5bcc\u5c71\u770c","addr":"\u5bcc\u5c71\u5e02\u5ca9\u702c\u8d64\u7530\u753a"},"9318372":{"pref":"\u5bcc\u5c71\u770c","addr":"\u5bcc\u5c71\u5e02\u5ca9\u702c\u5929\u6c60\u753a"},"9318346":{"pref":"\u5bcc\u5c71\u770c","addr":"\u5bcc\u5c71\u5e02\u5ca9\u702c\u8352\u6728\u753a"},"9318376":{"pref":"\u5bcc\u5c71\u770c","addr":"\u5bcc\u5c71\u5e02\u5ca9\u702c\u6c60\u7530\u753a"},"9318365":{"pref":"\u5bcc\u5c71\u770c","addr":"\u5bcc\u5c71\u5e02\u5ca9\u702c\u5165\u8239\u753a"},"9318362":{"pref":"\u5bcc\u5c71\u770c","addr":"\u5bcc\u5c71\u5e02\u5ca9\u702c\u6885\u672c\u753a"},"9318356":{"pref":"\u5bcc\u5c71\u770c","addr":"\u5bcc\u5c71\u5e02\u5ca9\u702c\u5927\u753a"},"9318341":{"pref":"\u5bcc\u5c71\u770c","addr":"\u5bcc\u5c71\u5e02\u5ca9\u702c\u5fa1\u8535\u753a"},"9318352":{"pref":"\u5bcc\u5c71\u770c","addr":"\u5bcc\u5c71\u5e02\u5ca9\u702c\u8868\u753a"},"9318354":{"pref":"\u5bcc\u5c71\u770c","addr":"\u5bcc\u5c71\u5e02\u5ca9\u702c\u7947\u5712\u753a"},"9318371":{"pref":"\u5bcc\u5c71\u770c","addr":"\u5bcc\u5c71\u5e02\u5ca9\u702c\u53e4\u5fd7\u753a"},"9318343":{"pref":"\u5bcc\u5c71\u770c","addr":"\u5bcc\u5c71\u5e02\u5ca9\u702c\u5e78\u753a"},"9318351":{"pref":"\u5bcc\u5c71\u770c","addr":"\u5bcc\u5c71\u5e02\u5ca9\u702c\u583a\u753a"},"9318344":{"pref":"\u5bcc\u5c71\u770c","addr":"\u5bcc\u5c71\u5e02\u5ca9\u702c\u65b0\u753a"},"9318342":{"pref":"\u5bcc\u5c71\u770c","addr":"\u5bcc\u5c71\u5e02\u5ca9\u702c\u795e\u660e\u753a"},"9318377":{"pref":"\u5bcc\u5c71\u770c","addr":"\u5bcc\u5c71\u5e02\u5ca9\u702c\u8acf\u8a2a\u753a"},"9318375":{"pref":"\u5bcc\u5c71\u770c","addr":"\u5bcc\u5c71\u5e02\u5ca9\u702c\u9ad8\u7560\u753a"},"9318378":{"pref":"\u5bcc\u5c71\u770c","addr":"\u5bcc\u5c71\u5e02\u5ca9\u702c\u5929\u795e\u753a"},"9318347":{"pref":"\u5bcc\u5c71\u770c","addr":"\u5bcc\u5c71\u5e02\u5ca9\u702c\u571f\u5834\u753a"},"9318363":{"pref":"\u5bcc\u5c71\u770c","addr":"\u5bcc\u5c71\u5e02\u5ca9\u702c\u4ef2\u753a"},"9318355":{"pref":"\u5bcc\u5c71\u770c","addr":"\u5bcc\u5c71\u5e02\u5ca9\u702c\u65b0\u5ddd\u753a"},"9318366":{"pref":"\u5bcc\u5c71\u770c","addr":"\u5bcc\u5c71\u5e02\u5ca9\u702c\u8429\u6d66\u753a"},"9318361":{"pref":"\u5bcc\u5c71\u770c","addr":"\u5bcc\u5c71\u5e02\u5ca9\u702c\u767d\u5c71\u753a"},"9318357":{"pref":"\u5bcc\u5c71\u770c","addr":"\u5bcc\u5c71\u5e02\u5ca9\u702c\u798f\u6765\u753a"},"9318353":{"pref":"\u5bcc\u5c71\u770c","addr":"\u5bcc\u5c71\u5e02\u5ca9\u702c\u6587\u5316\u753a"},"9318373":{"pref":"\u5bcc\u5c71\u770c","addr":"\u5bcc\u5c71\u5e02\u5ca9\u702c\u524d\u7530\u753a"},"9318367":{"pref":"\u5bcc\u5c71\u770c","addr":"\u5bcc\u5c71\u5e02\u5ca9\u702c\u677e\u539f\u753a"},"9318364":{"pref":"\u5bcc\u5c71\u770c","addr":"\u5bcc\u5c71\u5e02\u5ca9\u702c\u6e2f\u753a"},"9318327":{"pref":"\u5bcc\u5c71\u770c","addr":"\u5bcc\u5c71\u5e02\u4e0a\u91ce\u65b0"},"9318326":{"pref":"\u5bcc\u5c71\u770c","addr":"\u5bcc\u5c71\u5e02\u4e0a\u91ce\u65b0\u753a"},"9318405":{"pref":"\u5bcc\u5c71\u770c","addr":"\u5bcc\u5c71\u5e02\u6d77\u5cb8\u901a"},"9318407":{"pref":"\u5bcc\u5c71\u770c","addr":"\u5bcc\u5c71\u5e02\u6d77\u5cb8\u901a\u65b0\u753a"},"9318404":{"pref":"\u5bcc\u5c71\u770c","addr":"\u5bcc\u5c71\u5e02\u52a0\u53e4\u753a"},"9318451":{"pref":"\u5bcc\u5c71\u770c","addr":"\u5bcc\u5c71\u5e02\u9280\u5dba\u753a"},"9318442":{"pref":"\u5bcc\u5c71\u770c","addr":"\u5bcc\u5c71\u5e02\u6960\u6728"},"9318411":{"pref":"\u5bcc\u5c71\u770c","addr":"\u5bcc\u5c71\u5e02\u9ad8\u6765"},"9318417":{"pref":"\u5bcc\u5c71\u770c","addr":"\u5bcc\u5c71\u5e02\u53e4\u5fd7\u753a"},"9318435":{"pref":"\u5bcc\u5c71\u770c","addr":"\u5bcc\u5c71\u5e02\u5c0f\u897f"},"9318443":{"pref":"\u5bcc\u5c71\u770c","addr":"\u5bcc\u5c71\u5e02\u4e0b\u98ef\u91ce"},"9318325":{"pref":"\u5bcc\u5c71\u770c","addr":"\u5bcc\u5c71\u5e02\u57ce\u5ddd\u539f"},"9318454":{"pref":"\u5bcc\u5c71\u770c","addr":"\u5bcc\u5c71\u5e02\u4f4f\u53cb\u753a"},"9318409":{"pref":"\u5bcc\u5c71\u770c","addr":"\u5bcc\u5c71\u5e02\u6e05\u98a8\u753a"},"9318441":{"pref":"\u5bcc\u5c71\u770c","addr":"\u5bcc\u5c71\u5e02\u9ad8\u5cf6"},"9318315":{"pref":"\u5bcc\u5c71\u770c","addr":"\u5bcc\u5c71\u5e02\u9ad8\u5712\u753a"},"9318336":{"pref":"\u5bcc\u5c71\u770c","addr":"\u5bcc\u5c71\u5e02\u9ad8\u7560\u753a"},"9318403":{"pref":"\u5bcc\u5c71\u770c","addr":"\u5bcc\u5c71\u5e02\u7530\u7551"},"9318401":{"pref":"\u5bcc\u5c71\u770c","addr":"\u5bcc\u5c71\u5e02\u7530\u7551\u65b0\u753a"},"9318402":{"pref":"\u5bcc\u5c71\u770c","addr":"\u5bcc\u5c71\u5e02\u7530\u7551\u5317\u90e8"},"9318334":{"pref":"\u5bcc\u5c71\u770c","addr":"\u5bcc\u5c71\u5e02\u5343\u539f\u5d0e"},"9318445":{"pref":"\u5bcc\u5c71\u770c","addr":"\u5bcc\u5c71\u5e02\u9053\u6b63"},"9318316":{"pref":"\u5bcc\u5c71\u770c","addr":"\u5bcc\u5c71\u5e02\u8c4a\u4e18\u753a"},"9318322":{"pref":"\u5bcc\u5c71\u770c","addr":"\u5bcc\u5c71\u5e02\u8c4a\u5cf6\u753a"},"9318323":{"pref":"\u5bcc\u5c71\u770c","addr":"\u5bcc\u5c71\u5e02\u8c4a\u57ce\u65b0\u753a"},"9318324":{"pref":"\u5bcc\u5c71\u770c","addr":"\u5bcc\u5c71\u5e02\u8c4a\u57ce\u753a"},"9318311":{"pref":"\u5bcc\u5c71\u770c","addr":"\u5bcc\u5c71\u5e02\u8c4a\u7530"},"9318312":{"pref":"\u5bcc\u5c71\u770c","addr":"\u5bcc\u5c71\u5e02\u8c4a\u7530\u672c\u753a"},"9318313":{"pref":"\u5bcc\u5c71\u770c","addr":"\u5bcc\u5c71\u5e02\u8c4a\u7530\u753a"},"9318305":{"pref":"\u5bcc\u5c71\u770c","addr":"\u5bcc\u5c71\u5e02\u8c4a\u82e5\u753a"},"9318456":{"pref":"\u5bcc\u5c71\u770c","addr":"\u5bcc\u5c71\u5e02\u6c38\u4e45\u753a"},"9318453":{"pref":"\u5bcc\u5c71\u770c","addr":"\u5bcc\u5c71\u5e02\u4e2d\u7530"},"9318408":{"pref":"\u5bcc\u5c71\u770c","addr":"\u5bcc\u5c71\u5e02\u90a3\u667a\u753a"},"9318335":{"pref":"\u5bcc\u5c71\u770c","addr":"\u5bcc\u5c71\u5e02\u897f\u5bae\u753a"},"9318345":{"pref":"\u5bcc\u5c71\u770c","addr":"\u5bcc\u5c71\u5e02\u897f\u5bae"},"9318413":{"pref":"\u5bcc\u5c71\u770c","addr":"\u5bcc\u5c71\u5e02\u91ce\u7530"},"9318422":{"pref":"\u5bcc\u5c71\u770c","addr":"\u5bcc\u5c71\u5e02\u91ce\u4e2d"},"9318428":{"pref":"\u5bcc\u5c71\u770c","addr":"\u5bcc\u5c71\u5e02\u91ce\u4e2d\u65b0"},"9318333":{"pref":"\u5bcc\u5c71\u770c","addr":"\u5bcc\u5c71\u5e02\u84ee\u753a"},"9318414":{"pref":"\u5bcc\u5c71\u770c","addr":"\u5bcc\u5c71\u5e02\u6d5c\u9ed2\u5d0e"},"9318433":{"pref":"\u5bcc\u5c71\u770c","addr":"\u5bcc\u5c71\u5e02\u91dd\u539f\u65b0\u753a"},"9318432":{"pref":"\u5bcc\u5c71\u770c","addr":"\u5bcc\u5c71\u5e02\u91dd\u539f\u4e2d"},"9318415":{"pref":"\u5bcc\u5c71\u770c","addr":"\u5bcc\u5c71\u5e02\u91dd\u65e5"},"9318431":{"pref":"\u5bcc\u5c71\u770c","addr":"\u5bcc\u5c71\u5e02\u91dd\u539f\u4e2d\u753a"},"9318455":{"pref":"\u5bcc\u5c71\u770c","addr":"\u5bcc\u5c71\u5e02\u6674\u6d77\u53f0"},"9318358":{"pref":"\u5bcc\u5c71\u770c","addr":"\u5bcc\u5c71\u5e02\u6771\u5ca9\u702c\u753a"},"9318359":{"pref":"\u5bcc\u5c71\u770c","addr":"\u5bcc\u5c71\u5e02\u6771\u5ca9\u702c\u6751"},"9318444":{"pref":"\u5bcc\u5c71\u770c","addr":"\u5bcc\u5c71\u5e02\u6771\u30b1\u4e18"},"9318452":{"pref":"\u5bcc\u5c71\u770c","addr":"\u5bcc\u5c71\u5e02\u6771\u5bcc\u5c71\u5bff\u753a"},"9318416":{"pref":"\u5bcc\u5c71\u770c","addr":"\u5bcc\u5c71\u5e02\u65e5\u65b9\u6c5f"},"9318421":{"pref":"\u5bcc\u5c71\u770c","addr":"\u5bcc\u5c71\u5e02\u5e73\u698e"},"9318423":{"pref":"\u5bcc\u5c71\u770c","addr":"\u5bcc\u5c71\u5e02\u753a\u888b"},"9318406":{"pref":"\u5bcc\u5c71\u770c","addr":"\u5bcc\u5c71\u5e02\u677e\u6d66\u753a"},"9318434":{"pref":"\u5bcc\u5c71\u770c","addr":"\u5bcc\u5c71\u5e02\u4e09\u4e0a"},"9318301":{"pref":"\u5bcc\u5c71\u770c","addr":"\u5bcc\u5c71\u5e02\u6c34\u843d"},"9318427":{"pref":"\u5bcc\u5c71\u770c","addr":"\u5bcc\u5c71\u5e02\u5bae\u6761"},"9318436":{"pref":"\u5bcc\u5c71\u770c","addr":"\u5bcc\u5c71\u5e02\u5bae\u5712\u753a"},"9318425":{"pref":"\u5bcc\u5c71\u770c","addr":"\u5bcc\u5c71\u5e02\u5bae\u6210"},"9318426":{"pref":"\u5bcc\u5c71\u770c","addr":"\u5bcc\u5c71\u5e02\u5bae\u6210\u4e2d\u90e8"},"9318437":{"pref":"\u5bcc\u5c71\u770c","addr":"\u5bcc\u5c71\u5e02\u5bae\u753a"},"9318332":{"pref":"\u5bcc\u5c71\u770c","addr":"\u5bcc\u5c71\u5e02\u68ee"},"9318331":{"pref":"\u5bcc\u5c71\u770c","addr":"\u5bcc\u5c71\u5e02\u68ee\u4f4f\u753a"},"9318337":{"pref":"\u5bcc\u5c71\u770c","addr":"\u5bcc\u5c71\u5e02\u68ee\u82e5\u753a"},"9318412":{"pref":"\u5bcc\u5c71\u770c","addr":"\u5bcc\u5c71\u5e02\u6a2a\u8d8a"},"9318303":{"pref":"\u5bcc\u5c71\u770c","addr":"\u5bcc\u5c71\u5e02\u7c73\u7530"},"9318306":{"pref":"\u5bcc\u5c71\u770c","addr":"\u5bcc\u5c71\u5e02\u7c73\u7530\u3059\u305a\u304b\u3051\u53f0"},"9318304":{"pref":"\u5bcc\u5c71\u770c","addr":"\u5bcc\u5c71\u5e02\u7c73\u7530\u753a"},"9318302":{"pref":"\u5bcc\u5c71\u770c","addr":"\u5bcc\u5c71\u5e02\u7dd1\u967d\u753a"}}